botorchex/__init__.py
botorchex/acquisition/__init__.py
botorchex/acquisition/multi_objective/__init__.py
botorchex/acquisition/multi_objective/monte_carlo.py
botorchex-0.1.0.dist-info/METADATA
botorchex-0.1.0.dist-info/WHEEL
botorchex-0.1.0.dist-info/RECORD
