Metadata-Version: 2.1
Name: botorchex
Version: 0.1.0
Summary: 
Author: 0h-n0
Author-email: kbu94982@gmail.com
Requires-Python: >=3.11,<4.0
Classifier: Programming Language :: Python :: 3
Classifier: Programming Language :: Python :: 3.11
Requires-Dist: botorch (>=0.8.1,<0.9.0)
